pdb_eda-2.7.1.dist-info/RECORD
pdb_eda-2.7.1.dist-info/top_level.txt
pdb_eda-2.7.1.dist-info/entry_points.txt
pdb_eda-2.7.1.dist-info/WHEEL
pdb_eda-2.7.1.dist-info/METADATA
pdb_eda-2.7.1.dist-info/LICENSE
tests/test_pdb.py
tests/test_ccp4.py
tests/__init__.py
pdb_eda/utils.py
pdb_eda/singleStructure.py
pdb_eda/pdbParser.py
pdb_eda/optimizeParams.py
pdb_eda/multipleStructures.py
pdb_eda/generateParams.py
pdb_eda/fileUtils.py
pdb_eda/densityAnalysis.py
pdb_eda/cutils_setup.py
pdb_eda/cutils.cpython-311-x86_64-linux-gnu.so
pdb_eda/crystalContacts.py
pdb_eda/ccp4.py
pdb_eda/__main__.py
pdb_eda/__init__.py
pdb_eda/conf/optimized_params.json
pdb_eda/conf/f000_parameters.json.gz
