Metadata-Version: 2.1
Name: pdb-eda
Version: 2.7.1
Summary: Methods for analyzing electron density maps in wwPDB
Home-page: https://github.com/MoseleyBioinformaticsLab/pdb_eda
Author: Sen Yao, Hunter N.B. Moseley
Author-email: hunter.moseley@gmail.com
License: Modified Clear BSD License
Keywords: PDB,electron densiy map
Platform: any
Classifier: Development Status :: 4 - Beta
Classifier: Environment :: Console
Classifier: Intended Audience :: Developers
Classifier: Intended Audience :: Science/Research
Classifier: License :: OSI Approved :: BSD License
Classifier: Operating System :: OS Independent
Classifier: Programming Language :: Python :: 3.4
Classifier: Programming Language :: Python :: 3.5
Classifier: Programming Language :: Python :: 3.6
Classifier: Topic :: Scientific/Engineering :: Bio-Informatics
Classifier: Topic :: Software Development :: Libraries :: Python Modules
License-File: LICENSE
Requires-Dist: docopt >=0.6.2
Requires-Dist: jsonpickle >=1.4.1
Requires-Dist: numpy >=1.16.2
Requires-Dist: scipy >=1.2.1
Requires-Dist: biopython >=1.77
Requires-Dist: PyCifRW >=4.4.2
Requires-Dist: cython >=0.29.21
